{
    "name": "Focus (Rusty)",
    "appearance": "dark",
    "style": {
        "border": "#271e1c",
        "border.variant": "#271e1c",
        "border.focused": "#271e1c",
        "border.selected": "#271e1c",
        "border.transparent": "#271e1c",
        "border.disabled": "#271e1c",

        "elevated_surface.background": "#271e1c",

        "surface.background": "#2c2f33",
        "background": "#3b2e2a",
        "element.background": "#3b2e2a",
        "element.hover": "#31353b",
        "element.active": "#aba70a",
        "element.selected": "#4f545c",
        "element.disabled": "#42464d",
        "drop_target.background": "#2e3136",
        "ghost_element.background": "#3b2e2a",
        "ghost_element.hover": "#271e1c",
        "ghost_element.active": "#3b3f45",
        "ghost_element.selected": "#271e1c",
        "ghost_element.disabled": "#484c52",
        "text": "#acaeaf",
        "text.muted": "#828997",
        "text.placeholder": "#5c6370",
        "text.disabled": "#4b5263",
        "text.accent": "#fbc049",
        "icon": "#fbc049",
        "icon.muted": "#828997",
        "icon.disabled": "#4b5263",
        "icon.placeholder": "#5c6370",
        "icon.accent": "#fbc049",
        "status_bar.background": "#3b2e2a",
        "title_bar.background": "#3b2e2a",
        "toolbar.background": "#3b2e2a",
        "tab_bar.background": "#3b2e2a",
        "tab.inactive_background": "#3b2e2a",
        "tab.active_background": "#271e1c",
        "search.match_background": "#e9ecf2",
        "panel.background": "#3b2e2a",
        "panel.focused_border": "#3b2e2a",
        "pane.focused_border": "#3b2e2a",
        "scrollbar.thumb.background": "#3b2e2a",
        "scrollbar.thumb.hover_background": "#40474f",
        "scrollbar.thumb.border": "#271e1c",
        "scrollbar.track.background": "#3b2e2a",
        "scrollbar.track.border": "#3b2e2a",
        "editor.foreground": "#acaeaf",
        "editor.background": "#3b2e2a",
        "editor.gutter.background": "#3b2e2a",
        "editor.subheader.background": "#3b2e2a",
        "editor.active_line.background": "#271e1c",
        "editor.highlighted_line.background": "#271e1c",
        "editor.line_number": "#707375",
        "editor.active_line_number": "#Ea35EEE",
        "editor.invisible": "#3b4048",
        "editor.wrap_guide": "#40474f",
        "editor.active_wrap_guide": "#fbc049",
        "editor.document_highlight.read_background": "#343b45",
        "editor.document_highlight.write_background": "#40474f",
        "terminal.background": "#271e1c",
        "terminal.foreground": "#acaeaf",
        "terminal.bright_foreground": "#abb2bf",
        "terminal.dim_foreground": "#5c6370",
        "terminal.ansi.black": "#2c2f33",
        "terminal.ansi.bright_black": "#3b4048",
        "terminal.ansi.dim_black": "#343940",
        "terminal.ansi.red": "#Fb6e6E",
        "terminal.ansi.bright_red": "#be5046",
        "terminal.ansi.dim_red": "#69c998",
        "terminal.ansi.green": "#4a946e",
        "terminal.ansi.bright_green": "#4a946e",
        "terminal.ansi.dim_green": "#4a946e",
        "terminal.ansi.yellow": "#e5c07b",
        "terminal.ansi.bright_yellow": "#d19a66",
        "terminal.ansi.dim_yellow": "#e5c07b",
        "terminal.ansi.blue": "#8db16f",
        "terminal.ansi.bright_blue": "#8db16f",
        "terminal.ansi.dim_blue": "#8db16f",
        "terminal.ansi.magenta": "#6a4375",
        "terminal.ansi.bright_magenta": "#6a4375",
        "terminal.ansi.dim_magenta": "#6a4375",
        "terminal.ansi.cyan": "#56b6c2",
        "terminal.ansi.bright_cyan": "#56b6c2",
        "terminal.ansi.dim_cyan": "#56b6c2",
        "terminal.ansi.white": "#abb2bf",
        "terminal.ansi.bright_white": "#abb2bf",
        "terminal.ansi.dim_white": "#5c6370",
        "link_text.hover": "#fbc049",
        "conflict": "#d19a66",
        "conflict.background": "#271e1c",
        "conflict.border": "#3b2e2a",
        "created": "#4a946e",
        "created.background": "#271e1c",
        "created.border": "#545862",
        "deleted": "#69c998",
        "deleted.background": "#271e1c",
        "deleted.border": "#545862",
        "error": "#ff005e",
        "error.background": "#3b2e2a",
        "error.border": "#3b2e2a",
        "hidden": "#abb2bf",
        "hidden.background": "#271e1c",
        "hidden.border": "#545862",
        "hint": "#406C7A",
        "hint.background": "#3b2e2a",
        "hint.border": "#3b2e2a",
        "ignored": "#271e1c",
        "ignored.background": "#3b2e2a",
        "ignored.border": "#3b2e2a",
        "info": "#fbc049",
        "info.background": "#3b2e2a",
        "info.border": "#3b2e2a",
        "modified": "#FAC0A0",
        "modified.background": "#271e1c",
        "modified.border": "#545862",
        "predictive": "#7D7298",
        "predictive.background": "#3b2e2a",
        "predictive.border": "#3b2e2a",
        "renamed": "#FAEBA0",
        "renamed.background": "#271e1c",
        "renamed.border": "#545862",
        "success": "#4a946e",
        "success.background": "#271e1c",
        "success.border": "#545862",
        "unreachable": "#69c998",
        "unreachable.background": "#271e1c",
        "unreachable.border": "#545862",
        "warning": "#e5c07b",
        "warning.background": "#3b2e2a",
        "warning.border": "#3b2e2a",
        "players": [
            {
                "cursor": "#8da1c8",
                "selection": "#271e1c"
            }
        ],
        "syntax": {
            "attribute": {
                "color": "#FAA0FA",
                "font_style": null,
                "font_weight": 400
            },
            "comment": {
                "color": "#616876",
                "font_style": "italic",
                "font_weight": 400
            },
            "comment.doc": {
                "color": "#616876",
                "font_style": "italic",
                "font_weight": 400
            },
            "constant": {
                "color": "#bf80ff",
                "font_style": null,
                "font_weight": 500
            },
            "constructor": {
                "color": "#69c998",
                "font_style": null,
                "font_weight": null
            },
            "emphasis": {
                "color": "#acaeaf",
                "font_style": "italic",
                "font_weight": 700
            },
            "emphasis.strong": {
                "color": "#acaeaf",
                "font_style": "oblique",
                "font_weight": 600
            },
            "function": {
                "color": "#8db16f",
                "font_style": null,
                "font_weight": 400
            },
            "keyword": {
                "color": "#fe8019",
                "font_style": null,
                "font_weight": 400
            },
            "label": {
                "color": "#e5c07b",
                "font_style": null,
                "font_weight": null
            },
            "link_text": {
                "color": "#F18C8C",
                "font_style": null,
                "font_weight": null
            },
            "link_uri": {
                "color": "#F18C8C",
                "font_style": null,
                "font_weight": null
            },
            "number": {
                "color": "#b56fc7",
                "font_style": null,
                "font_weight": null
            },
            "operator": {
                "color": "#acaeaf",
                "font_style": null,
                "font_weight": null
            },
            "punctuation": {
                "color": "#acaeaf",
                "font_style": null,
                "font_weight": null
            },
            "punctuation.bracket": {
                "color": "#acaeaf",
                "font_style": null,
                "font_weight": null
            },
            "punctuation.delimiter": {
                "color": "#acaeaf",
                "font_style": null,
                "font_weight": null
            },
            "punctuation.list_marker": {
                "color": "#acaeaf",
                "font_style": null,
                "font_weight": null
            },
            "punctuation.special": {
                "color": "#acaeaf",
                "font_style": null,
                "font_weight": null
            },
            "property": {
                "color": "#56b6c2",
                "font_style": null,
                "font_weight": null
            },
            "string": {
                "color": "#e5c76d",
                "font_style": null,
                "font_weight": 400
            },
            "string.escape": {
                "color": "#f5d575",
                "font_style": null,
                "font_weight": null
            },
            "string.regex": {
                "color": "#fbda78",
                "font_style": null,
                "font_weight": null
            },
            "string.special": {
                "color": "#fbda78",
                "font_style": null,
                "font_weight": 600
            },
            "string.special.symbol": {
                "color": "#fbb778",
                "font_style": null,
                "font_weight": 700
            },
            "tag": {
                "color": "#99FFE4",
                "font_style": null,
                "font_weight": 900
            },
            "text.literal": {
                "color": "#acaeaf",
                "font_style": null,
                "font_weight": 400
            },
            "type": {
                "color": "#51a0aa",
                "font_style": null,
                "font_weight": 500
            },
            "variable": {
                "color": "#acaeaf",
                "font_style": null,
                "font_weight": 400
            },
            "variable.special": {
                "color": "#acaeaf",
                "font_style": null,
                "font_weight": 400
            },
            "variable.special.property": {
                "color": "#acaeaf",
                "font_style": null,
                "font_weight": 400
            },
            "variable.special.property.readonly": {
                "color": "#acaeaf",
                "font_style": null,
                "font_weight": 900
            },
            "title": {
                "color": "#F18C8C",
                "font_style": null,
                "font_weight": 700
            },
            "preproc": {
                "color": "#eb781a",
                "font_style": null,
                "font_weight": 500
            },
            "boolean": {
                "color": "#F18C8C",
                "font_style": null,
                "font_weight": 400
            },
            "identifier": {
                "color": "#a9b2b4",
                "font_style": null,
                "font_weight": 900
            },
            "expression": {
                "color": "#F18C8C",
                "font_style": null,
                "font_weight": 500
            }
        }
    }
}
